forecastflowml/__init__.py
forecastflowml/core.py
forecastflowml/direct_forecaster.py
forecastflowml/model_selection.py
forecastflowml/preprocessing.py
forecastflowml/utils.py
forecastflowml/data/loader.py
forecastflowml/data/walmart_m5/._SUCCESS.crc
forecastflowml/data/walmart_m5/.part-00000-1bfe35f3-0707-4344-adc9-e57355f8a192-c000.snappy.parquet.crc
forecastflowml/data/walmart_m5/_SUCCESS
forecastflowml/data/walmart_m5/part-00000-1bfe35f3-0707-4344-adc9-e57355f8a192-c000.snappy.parquet
forecastflowml-0.0.2.dist-info/METADATA
forecastflowml-0.0.2.dist-info/WHEEL
forecastflowml-0.0.2.dist-info/top_level.txt
forecastflowml-0.0.2.dist-info/RECORD
