Metadata-Version: 2.1
Name: forecastflowml
Version: 0.0.2
Summary: Scalable machine learning forecasting framework with Pyspark
Home-page: https://github.com/canerturkseven/forecastflowml
Author: Caner Turkseven
Author-email: canerturkseven@gmail.com
License: MIT
Classifier: License :: OSI Approved :: MIT License
Classifier: Operating System :: OS Independent
Classifier: Programming Language :: Python :: 3
Classifier: Programming Language :: Python :: 3.7
Classifier: Programming Language :: Python :: 3.8
Classifier: Programming Language :: Python :: 3.9
Classifier: Programming Language :: Python :: 3.10
Classifier: Programming Language :: Python :: 3.11
Requires-Python: >=3.7
Requires-Dist: pyspark[sql] (>=3.0)
Requires-Dist: python-dateutil (>=2.8)
Requires-Dist: scikit-learn (>=1.0)
Requires-Dist: pandas (<2.0)
Requires-Dist: pyspark[sql] (>=3.4) ; python_version >= "3.11"
Provides-Extra: dev
Requires-Dist: pytest ; extra == 'dev'
Requires-Dist: pytest-cov ; extra == 'dev'
Requires-Dist: black[jupyter] ; extra == 'dev'
Requires-Dist: flake8 ; extra == 'dev'
Requires-Dist: tox ; extra == 'dev'
Requires-Dist: lightgbm ; extra == 'dev'
Requires-Dist: xgboost ; extra == 'dev'
Provides-Extra: docs
Requires-Dist: sphinx (>=4.0.0) ; extra == 'docs'
Requires-Dist: pydata-sphinx-theme (==0.13.3) ; extra == 'docs'
Requires-Dist: sphinx-autobuild ; extra == 'docs'
Requires-Dist: myst-nb ; extra == 'docs'
Requires-Dist: plotly ; extra == 'docs'
Requires-Dist: lightgbm ; extra == 'docs'
